{
  "$schema": "http://json-schema.org/draft-06/schema",
  "description": "Configuration file for coc.nvim",
    "languageserver": {
	  "ccls": {
	    "command": "ccls",
	    "filetypes": ["c", "cuda", "cpp", "objc", "objcpp"],
	    "rootPatterns": [".ccls", "compile_commands.json", ".vim/", ".git/", ".hg/"],
	    "initializationOptions": {
	  	 "cache": {
	  	   "directory": "/tmp/ccls"
	  	 }
	     }
	  }
    },
    "python.linting.pylintArgs": [
        "----extension-pkg-whitelist=1xml"
    ]
}
